{
  "main": {
    "id": "9f1e61f9cd6f94b5",
    "type": "split",
    "children": [
      {
        "id": "d3615ca6559abcc0",
        "type": "tabs",
        "children": [
          {
            "id": "4a4a3f7fcebceec4",
            "type": "leaf",
            "pinned": true,
            "state": {
              "type": "markdown",
              "state": {
                "file": "Diary/2022-11-11.md",
                "mode": "source",
                "source": false
              },
              "pinned": true
            }
          },
          {
            "id": "b523cce7d9e38ae5",
            "type": "leaf",
            "state": {
              "type": "markdown",
              "state": {
                "file": "Diary/2022-11-27.md",
                "mode": "source",
                "source": false
              }
            }
          },
          {
            "id": "7a5a990854f5c86a",
            "type": "leaf",
            "state": {
              "type": "markdown",
              "state": {
                "file": "Diary/2022-11-15.md",
                "mode": "source",
                "source": false
              }
            }
          },
          {
            "id": "077d4e3dc57e9bca",
            "type": "leaf",
            "state": {
              "type": "markdown",
              "state": {
                "file": "PaperReading/MULUT.md",
                "mode": "source",
                "source": false
              }
            }
          },
          {
            "id": "990cabab032f1e83",
            "type": "leaf",
            "state": {
              "type": "markdown",
              "state": {
                "file": "Diary/2022-11-18.md",
                "mode": "source",
                "source": false
              }
            }
          },
          {
            "id": "0550658682816a7f",
            "type": "leaf",
            "state": {
              "type": "markdown",
              "state": {
                "file": "Diary/2022-11-22.md",
                "mode": "source",
                "source": false
              }
            }
          },
          {
            "id": "3ea94df3cb73c85b",
            "type": "leaf",
            "state": {
              "type": "markdown",
              "state": {
                "file": "Diary/2022-11-19.md",
                "mode": "source",
                "source": false
              }
            }
          },
          {
            "id": "6d8d6a69d3b7594c",
            "type": "leaf",
            "state": {
              "type": "markdown",
              "state": {
                "file": "AAAI比赛.md",
                "mode": "source",
                "source": false
              }
            }
          },
          {
            "id": "75c3ca2c42ade599",
            "type": "leaf",
            "state": {
              "type": "markdown",
              "state": {
                "file": "面向存算一体芯片量化感知的网络结构搜索技术研究.md",
                "mode": "source",
                "source": false
              }
            }
          },
          {
            "id": "6b31c2b922224131",
            "type": "leaf",
            "state": {
              "type": "markdown",
              "state": {
                "file": "RepOpt.md",
                "mode": "source",
                "source": false
              }
            }
          },
          {
            "id": "61a549651fd128e0",
            "type": "leaf",
            "state": {
              "type": "markdown",
              "state": {
                "file": "Optimizing Memory Acess in EDA + Algorithms, AI Accelerators and PIM Architectures.md",
                "mode": "source",
                "source": false
              }
            }
          },
          {
            "id": "704358ae38c922b8",
            "type": "leaf",
            "state": {
              "type": "markdown",
              "state": {
                "file": "Matplotlib技巧.md",
                "mode": "source",
                "source": false
              }
            }
          },
          {
            "id": "27e083a257f8457e",
            "type": "leaf",
            "state": {
              "type": "markdown",
              "state": {
                "file": "面向存算一体芯片量化感知的网络结构搜索技术研究.md",
                "mode": "source",
                "source": false
              }
            }
          },
          {
            "id": "1c98f1735130bea5",
            "type": "leaf",
            "state": {
              "type": "markdown",
              "state": {
                "file": "Verilog复习与进阶.md",
                "mode": "source",
                "source": false
              }
            }
          }
        ],
        "currentTab": 1
      }
    ],
    "direction": "vertical"
  },
  "left": {
    "id": "39812d7f6f2d79ae",
    "type": "split",
    "children": [
      {
        "id": "98d4a25abfcb8bff",
        "type": "tabs",
        "children": [
          {
            "id": "3001044a26f65957",
            "type": "leaf",
            "state": {
              "type": "file-explorer",
              "state": {
                "sortOrder": "alphabetical"
              }
            }
          },
          {
            "id": "02f2d5dc04fd962a",
            "type": "leaf",
            "state": {
              "type": "search",
              "state": {
                "query": "",
                "matchingCase": false,
                "explainSearch": false,
                "collapseAll": false,
                "extraContext": false,
                "sortOrder": "alphabetical"
              }
            }
          },
          {
            "id": "b14dc6a6ded70ae4",
            "type": "leaf",
            "state": {
              "type": "starred",
              "state": {}
            }
          }
        ]
      }
    ],
    "direction": "horizontal",
    "width": 300,
    "collapsed": true
  },
  "right": {
    "id": "1667fb34c1dc9c0f",
    "type": "split",
    "children": [
      {
        "id": "505aff7801c86fc3",
        "type": "tabs",
        "children": [
          {
            "id": "9766c0d0bc74a8e5",
            "type": "leaf",
            "state": {
              "type": "backlink",
              "state": {
                "file": "Diary/2022-11-27.md",
                "collapseAll": false,
                "extraContext": false,
                "sortOrder": "alphabetical",
                "showSearch": false,
                "searchQuery": "",
                "backlinkCollapsed": false,
                "unlinkedCollapsed": true
              }
            }
          },
          {
            "id": "18e7a19d9ff97223",
            "type": "leaf",
            "state": {
              "type": "outgoing-link",
              "state": {
                "file": "Diary/2022-11-27.md",
                "linksCollapsed": false,
                "unlinkedCollapsed": true
              }
            }
          },
          {
            "id": "3cc3d233373c3e3a",
            "type": "leaf",
            "state": {
              "type": "tag",
              "state": {
                "sortOrder": "frequency",
                "useHierarchy": true
              }
            }
          },
          {
            "id": "e25e827cf4978492",
            "type": "leaf",
            "state": {
              "type": "outline",
              "state": {
                "file": "Diary/2022-11-27.md"
              }
            }
          }
        ],
        "currentTab": 3
      }
    ],
    "direction": "horizontal",
    "width": 300
  },
  "active": "b523cce7d9e38ae5",
  "lastOpenFiles": [
    "Diary/2022-11-11.md",
    "Diary/2022-11-26.md",
    "Diary/2022-11-25.md",
    "未命名 3.md",
    "Matplotlib技巧.md",
    "Optimizing Memory Acess in EDA + Algorithms, AI Accelerators and PIM Architectures.md",
    "RepOpt.md",
    "面向存算一体芯片量化感知的网络结构搜索技术研究.md",
    "AAAI比赛.md",
    "毕设准备.md"
  ]
}